exact_multiset_cover/__init__.py
exact_multiset_cover/error.py
exact_multiset_cover/helpers.py
exact_multiset_cover/io.py
exact_multiset_cover/wrapper.py
exact_multiset_cover_impl.cpython-312-x86_64-linux-gnu.so
exact_multiset_cover-1.5.1.dist-info/LICENSE
exact_multiset_cover-1.5.1.dist-info/METADATA
exact_multiset_cover-1.5.1.dist-info/WHEEL
exact_multiset_cover-1.5.1.dist-info/entry_points.txt
exact_multiset_cover-1.5.1.dist-info/RECORD
