Metadata-Version: 2.3
Name: exact_multiset_cover
Version: 1.5.1
Summary: Solve exact cover problems for multisets. Fork of exact_cover
License: GPL-2.0-only
Author: Moy Easwaran
Maintainer: Jack Grahl
Maintainer-email: jack.grahl@gmail.com
Requires-Python: >=3.7,<4.0
Classifier: License :: OSI Approved :: GNU General Public License v2 (GPLv2)
Classifier: Programming Language :: Python :: 3
Classifier: Programming Language :: Python :: 3.7
Classifier: Programming Language :: Python :: 3.8
Classifier: Programming Language :: Python :: 3.9
Classifier: Programming Language :: Python :: 3.10
Classifier: Programming Language :: Python :: 3.11
Classifier: Programming Language :: Python :: 3.12
Classifier: Programming Language :: Python :: 3.13
Requires-Dist: numpy (>=1.14) ; python_version == "3.7"
Requires-Dist: numpy (>=1.17) ; python_version == "3.8"
Requires-Dist: numpy (>=1.19) ; python_version == "3.9"
Requires-Dist: numpy (>=1.21) ; python_version == "3.10"
Requires-Dist: numpy (>=1.23) ; python_version == "3.11"
Requires-Dist: numpy (>=1.24) ; python_version >= "3.12"
Requires-Dist: setuptools (>=51.1.2)
Project-URL: Homepage, https://github.com/questforwisdom/exact_multiset_cover
Project-URL: Repository, https://github.com/questforwisdom/exact_multiset_cover
